jsonschema_to_zon/__init__.py
jsonschema_to_zon/schema.py
jsonschema_to_zon-1.0.0.dist-info/licenses/LICENSE
jsonschema_to_zon-1.0.0.dist-info/METADATA
jsonschema_to_zon-1.0.0.dist-info/WHEEL
jsonschema_to_zon-1.0.0.dist-info/top_level.txt
jsonschema_to_zon-1.0.0.dist-info/RECORD
