Metadata-Version: 2.4
Name: jsonschema-to-zon
Version: 1.0.0
Summary: A library that allows converting from a JSON Schema document to a Zon-compatible validator.
Author-email: Nuno Pereira <nunoafonso2002@gmail.com>
Maintainer-email: Nuno Pereira <nunoafonso2002@gmail.com>
License-Expression: MIT
Project-URL: Homepage, https://github.com/Naapperas/jsonschema-to-zon
Project-URL: Issues, https://github.com/Naapperas/jsonschema-to-zon/issues
Keywords: zon,jsonschema,jsonschema-to-zon
Classifier: Programming Language :: Python :: 3
Classifier: Operating System :: OS Independent
Requires-Python: >=3.13
License-File: LICENSE
Requires-Dist: zon==2.0.1
Dynamic: license-file
